LICENSE.txt
MANIFEST.in
README.md
pyproject.toml
src/mf_prior_bench.egg-info/PKG-INFO
src/mf_prior_bench.egg-info/SOURCES.txt
src/mf_prior_bench.egg-info/dependency_links.txt
src/mf_prior_bench.egg-info/requires.txt
src/mf_prior_bench.egg-info/top_level.txt
src/mfpbench/__init__.py
src/mfpbench/__main__.py
src/mfpbench/benchmark.py
src/mfpbench/config.py
src/mfpbench/correlations.py
src/mfpbench/get.py
src/mfpbench/metric.py
src/mfpbench/priors.py
src/mfpbench/result.py
src/mfpbench/resultframe.py
src/mfpbench/setup_benchmark.py
src/mfpbench/stats.py
src/mfpbench/tabular.py
src/mfpbench/util.py
src/mfpbench/__pycache__/__init__.cpython-310.pyc
src/mfpbench/__pycache__/__main__.cpython-310.pyc
src/mfpbench/__pycache__/benchmark.cpython-310.pyc
src/mfpbench/__pycache__/config.cpython-310.pyc
src/mfpbench/__pycache__/get.cpython-310.pyc
src/mfpbench/__pycache__/metric.cpython-310.pyc
src/mfpbench/__pycache__/priors.cpython-310.pyc
src/mfpbench/__pycache__/result.cpython-310.pyc
src/mfpbench/__pycache__/resultframe.cpython-310.pyc
src/mfpbench/__pycache__/setup_benchmark.cpython-310.pyc
src/mfpbench/__pycache__/stats.cpython-310.pyc
src/mfpbench/__pycache__/tabular.cpython-310.pyc
src/mfpbench/__pycache__/util.cpython-310.pyc
src/mfpbench/jahs/__init__.py
src/mfpbench/jahs/benchmark.py
src/mfpbench/jahs/__pycache__/__init__.cpython-310.pyc
src/mfpbench/jahs/__pycache__/benchmark.cpython-310.pyc
src/mfpbench/lcbench_tabular/__init__.py
src/mfpbench/lcbench_tabular/benchmark.py
src/mfpbench/lcbench_tabular/__pycache__/__init__.cpython-310.pyc
src/mfpbench/lcbench_tabular/__pycache__/benchmark.cpython-310.pyc
src/mfpbench/nb201_tabular/__init__.py
src/mfpbench/nb201_tabular/benchmark.py
src/mfpbench/nb201_tabular/try_parse_nb201.py
src/mfpbench/nb201_tabular/__pycache__/__init__.cpython-310.pyc
src/mfpbench/nb201_tabular/__pycache__/benchmark.cpython-310.pyc
src/mfpbench/pd1/__init__.py
src/mfpbench/pd1/benchmark.py
src/mfpbench/pd1/__pycache__/__init__.cpython-310.pyc
src/mfpbench/pd1/__pycache__/benchmark.cpython-310.pyc
src/mfpbench/pd1/benchmarks/__init__.py
src/mfpbench/pd1/benchmarks/cifar100.py
src/mfpbench/pd1/benchmarks/imagenet.py
src/mfpbench/pd1/benchmarks/lm1b.py
