Metadata-Version: 2.2
Name: mf-prior-bench
Version: 1.10.0
Summary: A wrapper for multi-fidelity benchmarks with priors
Author-email: Eddie Bergman <eddiebergmanhs@gmail.com>
License:                               Apache License
Classifier: Intended Audience :: Science/Research
Classifier: Intended Audience :: Developers
Classifier: License :: OSI Approved
Classifier: Programming Language :: Python
Classifier: Topic :: Software Development
Classifier: Topic :: Scientific/Engineering
Classifier: Operating System :: POSIX
Classifier: Operating System :: Unix
Classifier: Operating System :: MacOS
Classifier: Programming Language :: Python :: 3
Classifier: Programming Language :: Python :: 3.10
Classifier: Programming Language :: Python :: 3.11
Requires-Python: >=3.10
License-File: LICENSE.txt
Requires-Dist: pyyaml
Requires-Dist: numpy<2.0
Requires-Dist: configspace>=1.0
Requires-Dist: pandas
Requires-Dist: more_itertools
Requires-Dist: pyarrow
Provides-Extra: yahpo
Requires-Dist: yahpo-gym==1.0.1; extra == "yahpo"
Provides-Extra: jahs-bench
Requires-Dist: jahs_bench==1.2.0; extra == "jahs-bench"
Requires-Dist: pandas<2.0; extra == "jahs-bench"
Requires-Dist: numpy<2.0.0; extra == "jahs-bench"
Provides-Extra: tabular
Requires-Dist: pandas>2; extra == "tabular"
Requires-Dist: pyarrow; extra == "tabular"
Provides-Extra: pd1
Requires-Dist: xgboost[scikit-learn]>=1.7; extra == "pd1"
Provides-Extra: taskset-tabular
Requires-Dist: tensorflow<=2.18.0; extra == "taskset-tabular"
Provides-Extra: surrogates
Requires-Dist: dehb; extra == "surrogates"
Provides-Extra: docs
Requires-Dist: mkdocs; extra == "docs"
Requires-Dist: mike; extra == "docs"
Requires-Dist: mkdocs-material; extra == "docs"
Requires-Dist: mkdocs-gen-files; extra == "docs"
Requires-Dist: mkdocs-literate-nav; extra == "docs"
Requires-Dist: mkdocs-autorefs; extra == "docs"
Requires-Dist: mkdocstrings[python]; extra == "docs"
Requires-Dist: markdown-exec[ansi]; extra == "docs"
Provides-Extra: dev
Requires-Dist: ruff; extra == "dev"
Requires-Dist: pytest; extra == "dev"
Requires-Dist: pytest-cov; extra == "dev"
Requires-Dist: pytest-cases; extra == "dev"
Requires-Dist: black; extra == "dev"
Requires-Dist: pre-commit; extra == "dev"
Requires-Dist: mypy; extra == "dev"
Requires-Dist: mf-prior-bench[docs,tabular]; extra == "dev"
